netdescribe
