Metadata-Version: 2.1
Name: netdescribe
Version: 0.2.8
Summary: Library of functions for performing discovery on network devices.
Home-page: https://github.com/equill/netdescribe
Author: James Fleming
Author-email: james@electronic-quill.net
License: Apachev2
Keywords: network,discovery,snmp
Platform: UNKNOWN
Classifier: Development Status :: 3 - Alpha
Classifier: Intended Audience :: System Administrators
Classifier: Intended Audience :: Telecommunications Industry
Classifier: Topic :: Software Development :: Libraries :: Python Modules
Classifier: Topic :: System :: Networking :: Monitoring
Classifier: License :: OSI Approved :: Apache Software License
Classifier: Programming Language :: Python :: 3
Classifier: Programming Language :: Python :: 3.9
License-File: LICENSE.txt
